Metadata-Version: 1.0
Name: django-autotest-command
Version: 1.5.1
Summary: 
